ddbt/__init__.py
ddbt/cli.py
ddbt/constants.py
ddbt/exceptions.py
ddbt/extra/jinja_functions.py
ddbt/task/base.py
ddbt/task/bootstrap_schema.py
ddbt/task/bootstrap_source.py
ddbt/task/extract.py
ddbt-0.2.5.dist-info/entry_points.txt
ddbt-0.2.5.dist-info/WHEEL
ddbt-0.2.5.dist-info/METADATA
ddbt-0.2.5.dist-info/RECORD
