Metadata-Version: 2.1
Name: ddbt
Version: 0.2.5
Summary: Command line tool that adds E (extract), L (load) and some other extra dev features to dbt (https://www.getdbt.com).
Home-page: https://github.com/tomsej/ddbt/
License: MIT
Keywords: dbt,data-modeling,elt,analytics,business-intelligence
Author: Radek Tomsej
Author-email: radek@tomsej.cz
Requires-Python: >=3.7,<4.0
Classifier: Development Status :: 3 - Alpha
Classifier: License :: OSI Approved :: MIT License
Classifier: Programming Language :: Python :: 3
Classifier: Programming Language :: Python :: 3.7
Classifier: Programming Language :: Python :: 3.8
Requires-Dist: attrs (>=19.3.0,<20.0.0)
Requires-Dist: dbt (>=0.17,<0.18)
Requires-Dist: hvac[parser] (>=0.10.2,<0.11.0)
Requires-Dist: python-dateutil (>=2.8.1,<3.0.0)
Project-URL: Repository, https://github.com/tomsej/ddbt/
Project-URL: issues, https://github.com/tomsej/ddbt/issues
